LICENSE
README.md
setup.cfg
setup.py
seesawloss/__init__.py
seesawloss/seesawloss.py
seesawloss.egg-info/PKG-INFO
seesawloss.egg-info/SOURCES.txt
seesawloss.egg-info/dependency_links.txt
seesawloss.egg-info/requires.txt
seesawloss.egg-info/top_level.txt