Metadata-Version: 2.1
Name: seesawloss
Version: 0.1.1
Summary: pytorch implementation of seesaw loss
Home-page: https://github.com/jahongir7174/SeesawLoss
Author: Jahongir Yunusov
Author-email: jahongir7174@gmail.com
License: MIT
Platform: UNKNOWN
Classifier: License :: OSI Approved :: MIT License
Classifier: Programming Language :: Python :: 3
Classifier: Programming Language :: Python :: 3.8
